minigrammar/__init__.py
minigrammar/exceptions.py
minigrammar/file_parser_iterator.py
minigrammar/language_settings.py
minigrammar/parsing.py
minigrammar/string_parser_iterator.py
minigrammar-0.1.0.dist-info/METADATA
minigrammar-0.1.0.dist-info/WHEEL
minigrammar-0.1.0.dist-info/licenses/LICENSE
minigrammar-0.1.0.dist-info/RECORD
