Metadata-Version: 2.3
Name: minigrammar
Version: 0.1.0
Summary: A parser-generation library based on decorators
Author-email: Francesco De Rosa <francescodero@outlook.it>
License: MIT License
License-File: LICENSE
Requires-Python: >=3.8
